<?xml version="1.0"?>
<markers><marker lat="40.436036005233959" lng="-79.985455385193148" zone="Zone 2" incidentdate="2014-10-25" incidenttime="09:30:00" incidentnumber="13182271" address="1400 block Locust St" type="ARREST" description="*********************************************** &lt;br/&gt;3502, Burglary.&lt;br/&gt;"/><marker lat="40.436036005233959" lng="-79.985455385193148" zone="Zone 2" incidentdate="2014-10-25" incidenttime="00:20:00" incidentnumber="13182271" address="1400 block Locust St" type="OFFENSE" description="*********************************************** &lt;br/&gt;3502, Burglary.&lt;br/&gt;"/><marker lat="40.428799178836528" lng="-79.984145739682731" zone="Zone 3" incidentdate="2014-10-25" incidenttime="02:29:00" incidentnumber="14100865" address="S 14th St &amp; E Carson St" type="ARREST" description="*********************************************** &lt;br/&gt;2701(b)(1), Simple Assault - Fight or Scuffle Entered by Mutual Consent&lt;br/&gt;5503(a)(1), DISORDERLY CONDUCT - ENGAGE IN FIGHTING&lt;br/&gt;"/><marker lat="40.435117964984315" lng="-79.993138203602911" zone="Zone 2" incidentdate="2014-10-25" incidenttime="18:34:00" incidentnumber="14104958" address="900 block Second Ave" type="ARREST" description="*********************************************** &lt;br/&gt;9501, Bench Warrant&lt;br/&gt;13(a)(16), Possession of Controlled Substance&lt;br/&gt;"/><marker lat="40.4538415518075" lng="-80.065153503817712" zone="Zone 6" incidentdate="2014-10-25" incidenttime="09:00:00" incidentnumber="14172117" address="1300 block Jeffers St" type="OFFENSE" description="*********************************************** &lt;br/&gt;4304(a)(1), Endangering Welfare of Children - Course of Conduct Enhanced&lt;br/&gt;"/><marker lat="40.4538415518075" lng="-80.065153503817712" zone="Zone 6" incidentdate="2014-10-25" incidenttime="09:00:00" incidentnumber="14172117" address="1300 block Jeffers St" type="ARREST" description="*********************************************** &lt;br/&gt;4304(a)(1), Endangering Welfare of Children - Course of Conduct Enhanced&lt;br/&gt;"/><marker lat="40.441678617818503" lng="-80.035354134024743" zone="Zone 6" incidentdate="2014-10-25" incidenttime="09:00:00" incidentnumber="14172286" address="Wabash St" type="ARREST" description="*********************************************** &lt;br/&gt;4304(a)(1), Endangering Welfare of Children - Course of Conduct Enhanced&lt;br/&gt;, Enhanced&lt;br/&gt;"/><marker lat="40.455980613101872" lng="-80.060496592408953" zone="Zone 6" incidentdate="2014-10-25" incidenttime="19:38:00" incidentnumber="14189351" address="900 block Fairdale St" type="ARREST" description="*********************************************** &lt;br/&gt;908, Prohibited Offensive Weapons.&lt;br/&gt;"/><marker lat="40.441371364794612" lng="-80.00389725761795" zone="Zone 2" incidentdate="2014-10-25" incidenttime="00:05:00" incidentnumber="14212499" address="Liberty Ave &amp; Stanwix St" type="OFFENSE" description="*********************************************** &lt;br/&gt;3111, Obedience to Traffic-Control Devices.&lt;br/&gt;3802(a)(1), DUI - General Impairment&lt;br/&gt;3802(c), DUI - Highest Rate of Alcohol - BAC &gt;= .16%&lt;br/&gt;"/><marker lat="40.441371364794612" lng="-80.00389725761795" zone="Zone 2" incidentdate="2014-10-25" incidenttime="00:05:00" incidentnumber="14212499" address="Liberty Ave &amp; Stanwix St" type="ARREST" description="*********************************************** &lt;br/&gt;3111, Obedience to Traffic-Control Devices.&lt;br/&gt;3802(a)(1), DUI - General Impairment&lt;br/&gt;3802(c), DUI - Highest Rate of Alcohol - BAC &gt;= .16%&lt;br/&gt;"/><marker lat="40.428585203983602" lng="-79.981869007680203" zone="Zone 3" incidentdate="2014-10-25" incidenttime="00:12:00" incidentnumber="14212508" address="1700 block E Carson St" type="OFFENSE" description="*********************************************** &lt;br/&gt;3503(b)(1)(i), Actual Communication&lt;br/&gt;"/><marker lat="40.428585203983602" lng="-79.981869007680203" zone="Zone 3" incidentdate="2014-10-25" incidenttime="00:12:00" incidentnumber="14212508" address="1700 block E Carson St" type="ARREST" description="*********************************************** &lt;br/&gt;3503(b)(1)(i), Actual Communication&lt;br/&gt;"/><marker lat="40.468749760081941" lng="-79.927499101456689" zone="Zone 5" incidentdate="2014-10-25" incidenttime="00:23:00" incidentnumber="14212514" address="Black St &amp; N Negley Ave" type="OFFENSE" description="*********************************************** &lt;br/&gt;2702, Aggravated Assault.&lt;br/&gt;901, Criminal Attempt&lt;br/&gt;903, Criminal Conspiracy.&lt;br/&gt;"/><marker lat="40.395865392846943" lng="-80.02206268719263" zone="Zone 6" incidentdate="2014-10-25" incidenttime="00:26:00" incidentnumber="14212520" address="2400 block Wedgemere St" type="OFFENSE" description="*********************************************** &lt;br/&gt;3745, Accidents Involving Damage to Unattended Veh.or Prop.&lt;br/&gt;"/><marker lat="40.428585203983602" lng="-79.981869007680203" zone="Zone 3" incidentdate="2014-10-25" incidenttime="00:55:00" incidentnumber="14212538" address="West Liberty Ave Ramp &amp; Saw Mill Run" type="OFFENSE" description="*********************************************** &lt;br/&gt;9999, 9999 - (Misc. Incident):&lt;br/&gt;"/><marker lat="40.393763350151033" lng="-80.014682709848969" zone="Zone 6" incidentdate="2014-10-25" incidenttime="01:06:00" incidentnumber="14212541" address="Edgebrook Ave &amp; Milan Ave" type="ARREST" description="*********************************************** &lt;br/&gt;3743, Accidents Involving Damage to Attended Veh. or Property&lt;br/&gt;3802(a)(1), DUI - General Impairment&lt;br/&gt;3802(c), DUI - Highest Rate of Alcohol - BAC &gt;= .16%&lt;br/&gt;"/><marker lat="40.393763350151033" lng="-80.014682709848969" zone="Zone 6" incidentdate="2014-10-25" incidenttime="00:54:00" incidentnumber="14212541" address="Edgebrook Ave &amp; Milan Ave" type="OFFENSE" description="*********************************************** &lt;br/&gt;3743, Accidents Involving Damage to Attended Veh. or Property&lt;br/&gt;3802(a)(1), DUI - General Impairment&lt;br/&gt;3802(c), DUI - Highest Rate of Alcohol - BAC &gt;= .16%&lt;br/&gt;"/><marker lat="40.433891542802876" lng="-79.960377840951992" zone="Zone 4" incidentdate="2014-10-25" incidenttime="01:00:00" incidentnumber="14212545" address="3200 block Niagara St" type="OFFENSE" description="*********************************************** &lt;br/&gt;601.16, Public Urination And Defecation&lt;br/&gt;6308(a), Underage Purchase, Consume, Possessed or Transport Liquor&lt;br/&gt;"/><marker lat="40.476489179820859" lng="-80.03171870815568" zone="Zone 1" incidentdate="2014-10-25" incidenttime="01:25:00" incidentnumber="14212551" address="Woods Run Ave &amp; Brighton Rd" type="OFFENSE" description="*********************************************** &lt;br/&gt;9501, Bench Warrant&lt;br/&gt;"/><marker lat="40.476489179820859" lng="-80.03171870815568" zone="Zone 1" incidentdate="2014-10-25" incidenttime="01:25:00" incidentnumber="14212551" address="Woods Run Ave &amp; Brighton Rd" type="ARREST" description="*********************************************** &lt;br/&gt;9501, Bench Warrant&lt;br/&gt;"/><marker lat="40.429418411414389" lng="-79.976177564961262" zone="Zone 3" incidentdate="2014-10-25" incidenttime="01:17:00" incidentnumber="14212554" address="Sidney St &amp; S 21st St" type="ARREST" description="*********************************************** &lt;br/&gt;3334, Turning Movements and Required Signals.&lt;br/&gt;3714, Careless Driving&lt;br/&gt;3323, Stop Signs and Yield Signs.&lt;br/&gt;3733, Fleeing or Attempting to Elude Police Officer&lt;br/&gt;"/><marker lat="40.429418411414389" lng="-79.976177564961262" zone="Zone 3" incidentdate="2014-10-25" incidenttime="01:17:00" incidentnumber="14212554" address="Sidney St &amp; S 21st St" type="OFFENSE" description="*********************************************** &lt;br/&gt;3334, Turning Movements and Required Signals.&lt;br/&gt;3714, Careless Driving&lt;br/&gt;3323, Stop Signs and Yield Signs.&lt;br/&gt;3733, Fleeing or Attempting to Elude Police Officer&lt;br/&gt;"/><marker lat="40.457235795591139" lng="-79.936388654634527" zone="Zone 5" incidentdate="2014-10-25" incidenttime="01:25:00" incidentnumber="14212558" address="5500 block Baum Blvd" type="ARREST" description="*********************************************** &lt;br/&gt;1301, Registration and Certificate of Title Required.&lt;br/&gt;1786, Required Financial Responsibility.&lt;br/&gt;3802(a)(1), DUI - General Impairment&lt;br/&gt;3802(c), DUI - Highest Rate of Alcohol - BAC &gt;= .16%&lt;br/&gt;"/><marker lat="40.457235795591139" lng="-79.936388654634527" zone="Zone 5" incidentdate="2014-10-25" incidenttime="01:21:00" incidentnumber="14212558" address="5500 block Baum Blvd" type="OFFENSE" description="*********************************************** &lt;br/&gt;1301, Registration and Certificate of Title Required.&lt;br/&gt;1786, Required Financial Responsibility.&lt;br/&gt;3802(a)(1), DUI - General Impairment&lt;br/&gt;3802(c), DUI - Highest Rate of Alcohol - BAC &gt;= .16%&lt;br/&gt;"/><marker lat="40.466134176829321" lng="-79.952223677259056" zone="Zone 5" incidentdate="2014-10-25" incidenttime="01:10:00" incidentnumber="14212559" address="Penn Ave &amp; Friendship Ave" type="OFFENSE" description="*********************************************** &lt;br/&gt;3701, Robbery.&lt;br/&gt;"/><marker lat="40.428746746224945" lng="-79.982646526389246" zone="Zone 3" incidentdate="2014-10-25" incidenttime="01:50:00" incidentnumber="14212579" address="1600 block E Carson St" type="OFFENSE" description="*********************************************** &lt;br/&gt;601.08(a), Alcohol or Liquor Consumption on Streets or Sidewalks&lt;br/&gt;"/><marker lat="40.437971042458713" lng="-79.992051967547354" zone="Zone 2" incidentdate="2014-10-25" incidenttime="02:05:00" incidentnumber="14212582" address="Forbes Ave &amp; Armstrong Tunl" type="ARREST" description="*********************************************** &lt;br/&gt;3714, Careless Driving&lt;br/&gt;5101, Obstructing Admin. of Law&lt;br/&gt;3802(a)(1), DUI - General Impairment&lt;br/&gt;5503(a)(3), DISORDERLY CONDUCT - OBSCENE LANG/GEST&lt;br/&gt;5505, Public Drunkenness&lt;br/&gt;"/><marker lat="40.437971042458713" lng="-79.992051967547354" zone="Zone 2" incidentdate="2014-10-25" incidenttime="02:05:00" incidentnumber="14212582" address="Forbes Ave &amp; Armstrong Tunl" type="OFFENSE" description="*********************************************** &lt;br/&gt;3714, Careless Driving&lt;br/&gt;5101, Obstructing Admin. of Law&lt;br/&gt;3802(a)(1), DUI - General Impairment&lt;br/&gt;5503(a)(3), DISORDERLY CONDUCT - OBSCENE LANG/GEST&lt;br/&gt;5505, Public Drunkenness&lt;br/&gt;"/><marker lat="40.437971042458713" lng="-79.992051967547354" zone="Zone 2" incidentdate="2014-10-25" incidenttime="02:15:00" incidentnumber="14212582" address="Forbes Ave &amp; Armstrong Tunl" type="ARREST" description="*********************************************** &lt;br/&gt;3714, Careless Driving&lt;br/&gt;5101, Obstructing Admin. of Law&lt;br/&gt;3802(a)(1), DUI - General Impairment&lt;br/&gt;5503(a)(3), DISORDERLY CONDUCT - OBSCENE LANG/GEST&lt;br/&gt;5505, Public Drunkenness&lt;br/&gt;"/><marker lat="40.457563513130026" lng="-79.997923771045023" zone="Zone 1" incidentdate="2014-10-25" incidenttime="01:56:00" incidentnumber="14212583" address="800 block Concord St" type="ARREST" description="*********************************************** &lt;br/&gt;6105(c)(9), Persons Not To Possess Use Manuf, Control Firearm&lt;br/&gt;13(a)(16), Possession of Controlled Substance&lt;br/&gt;4303, General Lighting Requirements.&lt;br/&gt;6106, Firearms not to be Carried without a License.&lt;br/&gt;3334, Turning Movements and Required Signals.&lt;br/&gt;3925, Receiving Stolen Property.&lt;br/&gt;3802(a)(1), DUI - General Impairment&lt;br/&gt;3802(b), DUI - High Rate of Alchol - BAC &gt;=.10% &lt;.16%&lt;br/&gt;13(a)(31), Marijuana: Possession Small Amount&lt;br/&gt;3731, Driving Under Influence of Alcohol or Controlled Substance&lt;br/&gt;1501, Drivers Required to be Licensed.&lt;br/&gt;9094, Recovered Stolen Vehicle (OUTSIDE CITY)&lt;br/&gt;"/><marker lat="40.457563513130026" lng="-79.997923771045023" zone="Zone 1" incidentdate="2014-10-25" incidenttime="01:50:00" incidentnumber="14212583" address="800 block Concord St" type="OFFENSE" description="*********************************************** &lt;br/&gt;6105(c)(9), Persons Not To Possess Use Manuf, Control Firearm&lt;br/&gt;13(a)(16), Possession of Controlled Substance&lt;br/&gt;4303, General Lighting Requirements.&lt;br/&gt;6106, Firearms not to be Carried without a License.&lt;br/&gt;3334, Turning Movements and Required Signals.&lt;br/&gt;3925, Receiving Stolen Property.&lt;br/&gt;3802(a)(1), DUI - General Impairment&lt;br/&gt;3802(b), DUI - High Rate of Alchol - BAC &gt;=.10% &lt;.16%&lt;br/&gt;13(a)(31), Marijuana: Possession Small Amount&lt;br/&gt;3731, Driving Under Influence of Alcohol or Controlled Substance&lt;br/&gt;1501, Drivers Required to be Licensed.&lt;br/&gt;9094, Recovered Stolen Vehicle (OUTSIDE CITY)&lt;br/&gt;"/><marker lat="40.457563513130026" lng="-79.997923771045023" zone="Zone 1" incidentdate="2014-10-25" incidenttime="01:56:00" incidentnumber="14212583" address="800 block Concord St" type="ARREST" description="*********************************************** &lt;br/&gt;6105(c)(9), Persons Not To Possess Use Manuf, Control Firearm&lt;br/&gt;13(a)(16), Possession of Controlled Substance&lt;br/&gt;4303, General Lighting Requirements.&lt;br/&gt;6106, Firearms not to be Carried without a License.&lt;br/&gt;3334, Turning Movements and Required Signals.&lt;br/&gt;3925, Receiving Stolen Property.&lt;br/&gt;3802(a)(1), DUI - General Impairment&lt;br/&gt;3802(b), DUI - High Rate of Alchol - BAC &gt;=.10% &lt;.16%&lt;br/&gt;13(a)(31), Marijuana: Possession Small Amount&lt;br/&gt;3731, Driving Under Influence of Alcohol or Controlled Substance&lt;br/&gt;1501, Drivers Required to be Licensed.&lt;br/&gt;9094, Recovered Stolen Vehicle (OUTSIDE CITY)&lt;br/&gt;"/><marker lat="40.452311125710239" lng="-79.926715681479251" zone="Zone 4" incidentdate="2014-10-25" incidenttime="02:02:00" incidentnumber="14212585" address="900 block College Ave" type="OFFENSE" description="*********************************************** &lt;br/&gt;13(a)(31), Marijuana: Possession Small Amount&lt;br/&gt;2701, Simple Assault.&lt;br/&gt;"/><marker lat="40.452311125710239" lng="-79.926715681479251" zone="Zone 4" incidentdate="2014-10-25" incidenttime="02:26:00" incidentnumber="14212585" address="900 block College Ave" type="ARREST" description="*********************************************** &lt;br/&gt;13(a)(31), Marijuana: Possession Small Amount&lt;br/&gt;2701, Simple Assault.&lt;br/&gt;"/><marker lat="40.452311125710239" lng="-79.926715681479251" zone="Zone 4" incidentdate="2014-10-25" incidenttime="02:26:00" incidentnumber="14212585" address="900 block College Ave" type="ARREST" description="*********************************************** &lt;br/&gt;13(a)(31), Marijuana: Possession Small Amount&lt;br/&gt;2701, Simple Assault.&lt;br/&gt;"/><marker lat="40.488209834026463" lng="-80.015158575586483" zone="Zone 1" incidentdate="2014-10-25" incidenttime="01:49:00" incidentnumber="14212588" address="3800 block East St" type="ARREST" description="*********************************************** &lt;br/&gt;9501, Bench Warrant&lt;br/&gt;"/><marker lat="40.488209834026463" lng="-80.015158575586483" zone="Zone 1" incidentdate="2014-10-25" incidenttime="01:49:00" incidentnumber="14212588" address="3800 block East St" type="OFFENSE" description="*********************************************** &lt;br/&gt;9501, Bench Warrant&lt;br/&gt;"/><marker lat="40.428567965192009" lng="-79.987317884623508" zone="Zone 3" incidentdate="2014-10-25" incidenttime="03:00:00" incidentnumber="14212607" address="1100 block E Carson St" type="ARREST" description="*********************************************** &lt;br/&gt;2702, Aggravated Assault.&lt;br/&gt;3304, Criminal Mischief.&lt;br/&gt;5503, Disorderly Conduct.&lt;br/&gt;"/><marker lat="40.428567965192009" lng="-79.987317884623508" zone="Zone 3" incidentdate="2014-10-25" incidenttime="02:55:00" incidentnumber="14212607" address="1100 block E Carson St" type="OFFENSE" description="*********************************************** &lt;br/&gt;2702, Aggravated Assault.&lt;br/&gt;3304, Criminal Mischief.&lt;br/&gt;5503, Disorderly Conduct.&lt;br/&gt;"/><marker lat="40.428749648408306" lng="-79.986422192206675" zone="Zone 3" incidentdate="2014-10-25" incidenttime="02:29:00" incidentnumber="14212622" address="S 12TH St &amp; E CARSON St" type="OFFENSE" description="*********************************************** &lt;br/&gt;5503, Disorderly Conduct.&lt;br/&gt;5121, Escape.&lt;br/&gt;5505, Public Drunkenness&lt;br/&gt;"/><marker lat="40.428749648408306" lng="-79.986422192206675" zone="Zone 3" incidentdate="2014-10-25" incidenttime="02:29:00" incidentnumber="14212622" address="S 12TH St &amp; E CARSON St" type="ARREST" description="*********************************************** &lt;br/&gt;5503, Disorderly Conduct.&lt;br/&gt;5121, Escape.&lt;br/&gt;5505, Public Drunkenness&lt;br/&gt;"/><marker lat="40.428749648408306" lng="-79.986422192206675" zone="Zone 3" incidentdate="2014-10-25" incidenttime="02:29:00" incidentnumber="14212622" address="S 12TH St &amp; E CARSON St" type="ARREST" description="*********************************************** &lt;br/&gt;5503, Disorderly Conduct.&lt;br/&gt;5121, Escape.&lt;br/&gt;5505, Public Drunkenness&lt;br/&gt;"/><marker lat="40.429443186533462" lng="-80.007407097435419" zone="Zone 3" incidentdate="2014-10-25" incidenttime="02:00:00" incidentnumber="14212625" address="300 block Shiloh St" type="OFFENSE" description="*********************************************** &lt;br/&gt;3745, Accidents Involving Damage to Unattended Veh.or Prop.&lt;br/&gt;"/><marker lat="40.459338126046291" lng="-79.914438597229775" zone="Zone 5" incidentdate="2014-10-25" incidenttime="05:28:00" incidentnumber="14212635" address="Hamilton Ave &amp; Enterprise St" type="ARREST" description="*********************************************** &lt;br/&gt;13(a)(16), Possession of Controlled Substance&lt;br/&gt;1543, Driving While Operating Privilege is Suspended or Revoked.&lt;br/&gt;Convict, enumerated in subsection (b)&lt;br/&gt;5503, Disorderly Conduct.&lt;br/&gt;5505, Public Drunkenness&lt;br/&gt;6106, Firearms not to be Carried without a License.&lt;br/&gt;3334, Turning Movements and Required Signals.&lt;br/&gt;5104, Resisting Arrest or Other Law Enforcement.&lt;br/&gt;6105(a)(1), Persons not to possess, use, manufacture, control, sell or transfer firearms: Former convict enumerated in subsection (b)&lt;br/&gt;"/><marker lat="40.459338126046291" lng="-79.914438597229775" zone="Zone 5" incidentdate="2014-10-25" incidenttime="03:15:00" incidentnumber="14212635" address="Hamilton Ave &amp; Enterprise St" type="OFFENSE" description="*********************************************** &lt;br/&gt;13(a)(16), Possession of Controlled Substance&lt;br/&gt;1543, Driving While Operating Privilege is Suspended or Revoked.&lt;br/&gt;Convict, enumerated in subsection (b)&lt;br/&gt;5503, Disorderly Conduct.&lt;br/&gt;5505, Public Drunkenness&lt;br/&gt;6106, Firearms not to be Carried without a License.&lt;br/&gt;3334, Turning Movements and Required Signals.&lt;br/&gt;5104, Resisting Arrest or Other Law Enforcement.&lt;br/&gt;6105(a)(1), Persons not to possess, use, manufacture, control, sell or transfer firearms: Former convict enumerated in subsection (b)&lt;br/&gt;"/><marker lat="40.459338126046291" lng="-79.914438597229775" zone="Zone 5" incidentdate="2014-10-25" incidenttime="03:25:00" incidentnumber="14212635" address="Hamilton Ave &amp; Enterprise St" type="ARREST" description="*********************************************** &lt;br/&gt;13(a)(16), Possession of Controlled Substance&lt;br/&gt;1543, Driving While Operating Privilege is Suspended or Revoked.&lt;br/&gt;Convict, enumerated in subsection (b)&lt;br/&gt;5503, Disorderly Conduct.&lt;br/&gt;5505, Public Drunkenness&lt;br/&gt;6106, Firearms not to be Carried without a License.&lt;br/&gt;3334, Turning Movements and Required Signals.&lt;br/&gt;5104, Resisting Arrest or Other Law Enforcement.&lt;br/&gt;6105(a)(1), Persons not to possess, use, manufacture, control, sell or transfer firearms: Former convict enumerated in subsection (b)&lt;br/&gt;"/><marker lat="40.452311125710239" lng="-79.926715681479251" zone="Zone 4" incidentdate="2014-10-25" incidenttime="03:23:00" incidentnumber="14212639" address="Bates St &amp; Technology Center Dr" type="OFFENSE" description="*********************************************** &lt;br/&gt;3714, Careless Driving&lt;br/&gt;3802(a)(1), DUI - General Impairment&lt;br/&gt;3802(c), DUI - Highest Rate of Alcohol - BAC &gt;= .16%&lt;br/&gt;"/><marker lat="40.452311125710239" lng="-79.926715681479251" zone="Zone 4" incidentdate="2014-10-25" incidenttime="03:38:00" incidentnumber="14212639" address="Bates St &amp; Technology Center Dr" type="ARREST" description="*********************************************** &lt;br/&gt;3714, Careless Driving&lt;br/&gt;3802(a)(1), DUI - General Impairment&lt;br/&gt;3802(c), DUI - Highest Rate of Alcohol - BAC &gt;= .16%&lt;br/&gt;"/><marker lat="40.423206672339532" lng="-79.965014274909791" zone="Zone 3" incidentdate="2014-10-25" incidenttime="01:06:00" incidentnumber="14212649" address="3000 block Jane St" type="ARREST" description="*********************************************** &lt;br/&gt;2702, Aggravated Assault.&lt;br/&gt;5104, Resisting Arrest or Other Law Enforcement.&lt;br/&gt;5505, Public Drunkenness&lt;br/&gt;5503(a)(2), DISORDERLY CONDUCT - UNREASONABLE NOISE&lt;br/&gt;6308(a), Underage Purchase, Consume, Possessed or Transport Liquor&lt;br/&gt;"/><marker lat="40.423206672339532" lng="-79.965014274909791" zone="Zone 3" incidentdate="2014-10-25" incidenttime="00:57:00" incidentnumber="14212649" address="3000 block Jane St" type="OFFENSE" description="*********************************************** &lt;br/&gt;2702, Aggravated Assault.&lt;br/&gt;5104, Resisting Arrest or Other Law Enforcement.&lt;br/&gt;5505, Public Drunkenness&lt;br/&gt;5503(a)(2), DISORDERLY CONDUCT - UNREASONABLE NOISE&lt;br/&gt;6308(a), Underage Purchase, Consume, Possessed or Transport Liquor&lt;br/&gt;"/><marker lat="40.454307782768687" lng="-79.946518733076431" zone="Zone 5" incidentdate="2014-10-25" incidenttime="03:46:00" incidentnumber="14212655" address="4900 block Baum Blvd" type="OFFENSE" description="*********************************************** &lt;br/&gt;4120, Identity Theft&lt;br/&gt;3925, Receiving Stolen Property.&lt;br/&gt;4106, Access Device Fraud&lt;br/&gt;"/><marker lat="40.407673415101883" lng="-80.027289942683566" zone="Zone 6" incidentdate="2014-10-25" incidenttime="03:30:00" incidentnumber="14212658" address="Belasco Ave &amp; Cagwin St" type="OFFENSE" description="*********************************************** &lt;br/&gt;3701, Robbery.&lt;br/&gt;"/><marker lat="40.417537707319021" lng="-79.926009928476859" zone="Zone 4" incidentdate="2014-10-25" incidenttime="05:30:00" incidentnumber="14212676" address="4600 block Browns Hill Rd" type="ARREST" description="*********************************************** &lt;br/&gt;2701, Simple Assault.&lt;br/&gt;6308(a), Underage Purchase, Consume, Possessed or Transport Liquor&lt;br/&gt;5503, Disorderly Conduct.&lt;br/&gt;"/><marker lat="40.417537707319021" lng="-79.926009928476859" zone="Zone 4" incidentdate="2014-10-25" incidenttime="05:11:00" incidentnumber="14212676" address="4600 block Browns Hill Rd" type="OFFENSE" description="*********************************************** &lt;br/&gt;2701, Simple Assault.&lt;br/&gt;6308(a), Underage Purchase, Consume, Possessed or Transport Liquor&lt;br/&gt;5503, Disorderly Conduct.&lt;br/&gt;"/><marker lat="40.428648361859814" lng="-79.988539143059356" zone="Zone 3" incidentdate="2014-10-25" incidenttime="03:15:00" incidentnumber="14212683" address="1000 block E Carson St" type="OFFENSE" description="*********************************************** &lt;br/&gt;2901, Kidnapping.&lt;br/&gt;901, Criminal Attempt&lt;br/&gt;"/><marker lat="40.416904055911154" lng="-80.038519155338633" zone="Zone 6" incidentdate="2014-10-25" incidenttime="06:15:00" incidentnumber="14212685" address="1300 block Crane Ave" type="OFFENSE" description="*********************************************** &lt;br/&gt;9999, 9999 - (Misc. Incident):&lt;br/&gt;"/><marker lat="40.44609264948722" lng="-79.954629798535109" zone="Zone 4" incidentdate="2014-10-25" incidenttime="06:00:00" incidentnumber="14212699" address="100 block Lytton Ave" type="OFFENSE" description="*********************************************** &lt;br/&gt;9496, Dead on Arrival (DOA)&lt;br/&gt;"/><marker lat="40.450097920159166" lng="-79.996288626032594" zone="Zone 1" incidentdate="2014-10-25" incidenttime="07:20:00" incidentnumber="14212701" address="700 block River Ave" type="OFFENSE" description="*********************************************** &lt;br/&gt;9488, False  Burglar Alarm&lt;br/&gt;"/><marker lat="40.410758711444451" lng="-79.9660447807792" zone="Zone 3" incidentdate="2014-10-25" incidenttime="06:30:00" incidentnumber="14212702" address="1000 block Parkwood Rd" type="OFFENSE" description="*********************************************** &lt;br/&gt;3503(b)(1)(ii), Defiant Trespass Notice Posted by Sign(s)&lt;br/&gt;"/><marker lat="40.465263633655731" lng="-79.952552309831887" zone="Zone 5" incidentdate="2014-10-25" incidenttime="07:38:00" incidentnumber="14212708" address="4400 block Milgate St" type="OFFENSE" description="*********************************************** &lt;br/&gt;9123, Miscellaneous Fire Other Investigation to Continue&lt;br/&gt;"/><marker lat="40.4538415518075" lng="-80.065153503817712" zone="Zone 6" incidentdate="2014-10-25" incidenttime="09:00:00" incidentnumber="14212740" address="1300 block Jeffers St" type="ARREST" description="*********************************************** &lt;br/&gt;1301, Registration and Certificate of Title Required.&lt;br/&gt;1543, Driving While Operating Privilege is Suspended or Revoked.&lt;br/&gt;1372, Unauthorized Transfer or Use of Registration.&lt;br/&gt;1786, Required Financial Responsibility.&lt;br/&gt;4703, Operation of Vehicle without Official Certif. of Inspection&lt;br/&gt;4914, False Identification to Law Enforcement Authorities&lt;br/&gt;9501, Bench Warrant&lt;br/&gt;"/><marker lat="40.4538415518075" lng="-80.065153503817712" zone="Zone 6" incidentdate="2014-10-25" incidenttime="09:00:00" incidentnumber="14212740" address="1300 block Jeffers St" type="OFFENSE" description="*********************************************** &lt;br/&gt;1301, Registration and Certificate of Title Required.&lt;br/&gt;1543, Driving While Operating Privilege is Suspended or Revoked.&lt;br/&gt;1372, Unauthorized Transfer or Use of Registration.&lt;br/&gt;1786, Required Financial Responsibility.&lt;br/&gt;4703, Operation of Vehicle without Official Certif. of Inspection&lt;br/&gt;4914, False Identification to Law Enforcement Authorities&lt;br/&gt;9501, Bench Warrant&lt;br/&gt;"/><marker lat="40.456574053804964" lng="-80.028718045771654" zone="Zone 1" incidentdate="2014-10-25" incidenttime="09:00:00" incidentnumber="14212747" address="1200 block Juniata St" type="OFFENSE" description="*********************************************** &lt;br/&gt;3304, Criminal Mischief.&lt;br/&gt;"/><marker lat="40.476567629719661" lng="-79.928060236571184" zone="Zone 5" incidentdate="2014-10-25" incidenttime="09:45:00" incidentnumber="14212756" address="1100 block Heths St" type="OFFENSE" description="*********************************************** &lt;br/&gt;2709, Harassment (Non-Specific)&lt;br/&gt;"/><marker lat="40.442619038472124" lng="-80.051370115303399" zone="Zone 6" incidentdate="2014-10-25" incidenttime="07:50:00" incidentnumber="14212758" address="1400 block Steuben St" type="OFFENSE" description="*********************************************** &lt;br/&gt;3304, Criminal Mischief.&lt;br/&gt;"/><marker lat="40.44799942333826" lng="-79.988692730605138" zone="Zone 5" incidentdate="2014-10-25" incidenttime="09:50:00" incidentnumber="14212760" address="6300 block Penn Ave" type="OFFENSE" description="*********************************************** &lt;br/&gt;13(a)(31), Marijuana: Possession Small Amount&lt;br/&gt;2701, Simple Assault.&lt;br/&gt;13(a)(30), Possession w/ Intent to Del. Controlled Substance&lt;br/&gt;"/><marker lat="40.44799942333826" lng="-79.988692730605138" zone="Zone 5" incidentdate="2014-10-25" incidenttime="09:55:00" incidentnumber="14212760" address="6300 block Penn Ave" type="ARREST" description="*********************************************** &lt;br/&gt;13(a)(31), Marijuana: Possession Small Amount&lt;br/&gt;2701, Simple Assault.&lt;br/&gt;13(a)(30), Possession w/ Intent to Del. Controlled Substance&lt;br/&gt;"/><marker lat="40.44799942333826" lng="-79.988692730605138" zone="Zone 5" incidentdate="2014-10-25" incidenttime="09:55:00" incidentnumber="14212760" address="6300 block Penn Ave" type="ARREST" description="*********************************************** &lt;br/&gt;13(a)(31), Marijuana: Possession Small Amount&lt;br/&gt;2701, Simple Assault.&lt;br/&gt;13(a)(30), Possession w/ Intent to Del. Controlled Substance&lt;br/&gt;"/><marker lat="40.466499083639228" lng="-80.029350787158137" zone="Zone 1" incidentdate="2014-10-25" incidenttime="02:30:00" incidentnumber="14212764" address="1300 block Ingham St" type="OFFENSE" description="*********************************************** &lt;br/&gt;3921, Theft by Unlawful Taking or Disposition.&lt;br/&gt;"/><marker lat="40.483041135050279" lng="-80.003896194315018" zone="Zone 1" incidentdate="2014-10-25" incidenttime="10:00:00" incidentnumber="14212765" address="500 block Mt Pleasant Rd" type="OFFENSE" description="*********************************************** &lt;br/&gt;3304, Criminal Mischief.&lt;br/&gt;"/><marker lat="40.42004424033162" lng="-79.972349587531838" zone="Zone 3" incidentdate="2014-10-25" incidenttime="09:00:00" incidentnumber="14212767" address="2400 block Cobden St" type="OFFENSE" description="*********************************************** &lt;br/&gt;3934, Theft from Vehicle&lt;br/&gt;"/><marker lat="40.387334894928699" lng="-79.99242391316929" zone="Zone 3" incidentdate="2014-10-25" incidenttime="10:20:00" incidentnumber="14212775" address="2300 block Lucina Ave" type="OFFENSE" description="*********************************************** &lt;br/&gt;3304, Criminal Mischief.&lt;br/&gt;"/><marker lat="40.456240254872455" lng="-79.956548175435003" zone="Zone 2" incidentdate="2014-10-25" incidenttime="10:35:00" incidentnumber="14212776" address="Lisbon St &amp; Webster Ave" type="OFFENSE" description="*********************************************** &lt;br/&gt;9489, Found Property&lt;br/&gt;"/><marker lat="40.382321930520909" lng="-79.999059762327946" zone="Zone 3" incidentdate="2014-10-25" incidenttime="10:00:00" incidentnumber="14212777" address="300 block Pinecastle St" type="OFFENSE" description="*********************************************** &lt;br/&gt;9496, Dead on Arrival (DOA)&lt;br/&gt;"/><marker lat="40.458098300132207" lng="-79.87542325369958" zone="Zone 5" incidentdate="2014-10-25" incidenttime="10:20:00" incidentnumber="14212780" address="8500 block Frankstown Ave" type="OFFENSE" description="*********************************************** &lt;br/&gt;2709(a), Harassment.&lt;br/&gt;"/><marker lat="40.449316372194595" lng="-79.914970461641502" zone="Zone 4" incidentdate="2014-10-25" incidenttime="08:30:00" incidentnumber="14212781" address="500 block Hastings St" type="OFFENSE" description="*********************************************** &lt;br/&gt;3502, Burglary.&lt;br/&gt;"/><marker lat="40.416192601732035" lng="-80.025299190128038" zone="Zone 6" incidentdate="2014-10-25" incidenttime="10:50:00" incidentnumber="14212784" address="1300 block Beechview Ave" type="OFFENSE" description="*********************************************** &lt;br/&gt;2709(a), Harassment.&lt;br/&gt;"/><marker lat="40.462465488954635" lng="-79.964926631215761" zone="Zone 2" incidentdate="2014-10-25" incidenttime="11:23:00" incidentnumber="14212805" address="3500 block Howley St" type="OFFENSE" description="*********************************************** &lt;br/&gt;9490, Missing Persons (18 and Over)&lt;br/&gt;"/><marker lat="40.403192284933496" lng="-79.988820245417102" zone="Zone 3" incidentdate="2014-10-25" incidenttime="09:30:00" incidentnumber="14212812" address="100 block Linnview Ave" type="OFFENSE" description="*********************************************** &lt;br/&gt;3921(a), Theft by Unlawful Taking or Disposition - Movable item&lt;br/&gt;"/><marker lat="40.470947586017772" lng="-80.02920416997145" zone="Zone 1" incidentdate="2014-10-25" incidenttime="10:00:00" incidentnumber="14212816" address="2900 block Breker St" type="OFFENSE" description="*********************************************** &lt;br/&gt;2709(a)(3), Harassment No Legitimate Purpose&lt;br/&gt;"/><marker lat="40.460594319900963" lng="-79.922716789802806" zone="Zone 5" incidentdate="2014-10-25" incidenttime="11:40:00" incidentnumber="14212820" address="6200 block Penn Ave" type="OFFENSE" description="*********************************************** &lt;br/&gt;3929, Retail Theft.&lt;br/&gt;"/><marker lat="40.460594319900963" lng="-79.922716789802806" zone="Zone 5" incidentdate="2014-10-25" incidenttime="12:10:00" incidentnumber="14212820" address="6200 block Penn Ave" type="ARREST" description="*********************************************** &lt;br/&gt;3929, Retail Theft.&lt;br/&gt;"/><marker lat="40.428465808222732" lng="-79.978964991503105" zone="Zone 3" incidentdate="2014-10-25" incidenttime="11:59:00" incidentnumber="14212827" address="1900 block E Carson St" type="OFFENSE" description="*********************************************** &lt;br/&gt;3929, Retail Theft.&lt;br/&gt;"/><marker lat="40.451661842496272" lng="-80.020536079782786" zone="Zone 1" incidentdate="2014-10-25" incidenttime="11:40:00" incidentnumber="14212830" address="1100 block Western Ave" type="OFFENSE" description="*********************************************** &lt;br/&gt;2702, Aggravated Assault.&lt;br/&gt;"/><marker lat="40.451661842496272" lng="-80.020536079782786" zone="Zone 1" incidentdate="2014-10-25" incidenttime="12:22:00" incidentnumber="14212834" address="East St Ramp &amp; East St" type="OFFENSE" description="*********************************************** &lt;br/&gt;5507, Obstructing Highways and Passages.&lt;br/&gt;"/><marker lat="40.466893342153426" lng="-79.893641407410328" zone="Zone 5" incidentdate="2014-10-25" incidenttime="12:32:00" incidentnumber="14212835" address="7200 block Lemington Ave" type="OFFENSE" description="*********************************************** &lt;br/&gt;3921(a), Theft by Unlawful Taking or Disposition - Movable item&lt;br/&gt;"/><marker lat="40.393957736297061" lng="-80.024746602168804" zone="Zone 6" incidentdate="2014-10-25" incidenttime="13:08:00" incidentnumber="14212859" address="500 block Woodbourne Ave" type="OFFENSE" description="*********************************************** &lt;br/&gt;9488, False  Burglar Alarm&lt;br/&gt;"/><marker lat="40.452556712279311" lng="-79.993525297243139" zone="Zone 1" incidentdate="2014-10-25" incidenttime="13:14:00" incidentnumber="14212864" address="Progress St &amp; Chesbro St" type="OFFENSE" description="*********************************************** &lt;br/&gt;1543, Driving While Operating Privilege is Suspended or Revoked.&lt;br/&gt;3714, Careless Driving&lt;br/&gt;4536, Bumpers.&lt;br/&gt;3743, Accidents Involving Damage to Attended Veh. or Property&lt;br/&gt;"/><marker lat="40.441903885913661" lng="-80.045463582335955" zone="Zone 6" incidentdate="2014-10-25" incidenttime="12:51:00" incidentnumber="14212872" address="1100 block Steuben St" type="OFFENSE" description="*********************************************** &lt;br/&gt;3304, Criminal Mischief.&lt;br/&gt;901, Criminal Attempt&lt;br/&gt;3934, Theft from Vehicle&lt;br/&gt;"/><marker lat="40.468099538634512" lng="-79.998763977101248" zone="Zone 1" incidentdate="2014-10-25" incidenttime="13:35:00" incidentnumber="14212875" address="Luella &amp; Heim St" type="OFFENSE" description="*********************************************** &lt;br/&gt;3301, Arson&lt;br/&gt;"/><marker lat="40.460594319900963" lng="-79.922716789802806" zone="Zone 5" incidentdate="2014-10-25" incidenttime="13:35:00" incidentnumber="14212876" address="6200 block Penn Ave" type="OFFENSE" description="*********************************************** &lt;br/&gt;3304, Criminal Mischief.&lt;br/&gt;907, Possessing Instruments of Crime.&lt;br/&gt;3929, Retail Theft.&lt;br/&gt;"/><marker lat="40.460594319900963" lng="-79.922716789802806" zone="Zone 5" incidentdate="2014-10-25" incidenttime="13:45:00" incidentnumber="14212876" address="6200 block Penn Ave" type="ARREST" description="*********************************************** &lt;br/&gt;3304, Criminal Mischief.&lt;br/&gt;907, Possessing Instruments of Crime.&lt;br/&gt;3929, Retail Theft.&lt;br/&gt;"/><marker lat="40.430028091967571" lng="-79.920633569588375" zone="Zone 4" incidentdate="2014-10-25" incidenttime="12:45:00" incidentnumber="14212879" address="2400 block Shady Ave" type="OFFENSE" description="*********************************************** &lt;br/&gt;3921, Theft by Unlawful Taking or Disposition.&lt;br/&gt;"/><marker lat="40.446314652723053" lng="-80.016316228653437" zone="Zone 1" incidentdate="2014-10-25" incidenttime="13:50:00" incidentnumber="14212894" address="100 block Art Rooney Ave" type="OFFENSE" description="*********************************************** &lt;br/&gt;13(a)(31), Marijuana: Possession Small Amount&lt;br/&gt;"/><marker lat="40.446314652723053" lng="-80.016316228653437" zone="Zone 1" incidentdate="2014-10-25" incidenttime="13:50:00" incidentnumber="14212894" address="100 block Art Rooney Ave" type="ARREST" description="*********************************************** &lt;br/&gt;13(a)(31), Marijuana: Possession Small Amount&lt;br/&gt;"/><marker lat="40.446314652723053" lng="-80.016316228653437" zone="Zone 1" incidentdate="2014-10-25" incidenttime="13:50:00" incidentnumber="14212894" address="100 block Art Rooney Ave" type="ARREST" description="*********************************************** &lt;br/&gt;13(a)(31), Marijuana: Possession Small Amount&lt;br/&gt;"/><marker lat="40.455276829291662" lng="-80.047672481194809" zone="Zone 6" incidentdate="2014-10-25" incidenttime="14:20:00" incidentnumber="14212900" address="2700 block Sacramento Ave" type="OFFENSE" description="*********************************************** &lt;br/&gt;3304, Criminal Mischief.&lt;br/&gt;"/><marker lat="40.463607741558079" lng="-80.021516758207738" zone="Zone 1" incidentdate="2014-10-25" incidenttime="14:31:00" incidentnumber="14212901" address="2200 block Brighton Rd" type="OFFENSE" description="*********************************************** &lt;br/&gt;2701, Simple Assault.&lt;br/&gt;2705, Recklessly Endangering Another Person.&lt;br/&gt;"/><marker lat="40.488081814906529" lng="-79.894317224387123" zone="Zone 5" incidentdate="2014-10-25" incidenttime="14:45:00" incidentnumber="14212902" address="900 block Freeport Rd" type="ARREST" description="*********************************************** &lt;br/&gt;3929, Retail Theft.&lt;br/&gt;"/><marker lat="40.488081814906529" lng="-79.894317224387123" zone="Zone 5" incidentdate="2014-10-25" incidenttime="14:20:00" incidentnumber="14212902" address="900 block Freeport Rd" type="OFFENSE" description="*********************************************** &lt;br/&gt;3929, Retail Theft.&lt;br/&gt;"/><marker lat="40.464546944591895" lng="-79.998424406611775" zone="Zone 1" incidentdate="2014-10-25" incidenttime="15:46:00" incidentnumber="14212946" address="100 block Brahm St" type="OFFENSE" description="*********************************************** &lt;br/&gt;9999, 9999 - (Misc. Incident):&lt;br/&gt;"/><marker lat="40.450804541052527" lng="-79.906346309907761" zone="Zone 4" incidentdate="2014-10-25" incidenttime="14:00:00" incidentnumber="14212973" address="7000 block Penn Ave" type="OFFENSE" description="*********************************************** &lt;br/&gt;3502, Burglary.&lt;br/&gt;"/><marker lat="40.387162017651526" lng="-79.985799751878702" zone="Zone 3" incidentdate="2014-10-25" incidenttime="16:40:00" incidentnumber="14212978" address="2300 block Edgar St" type="OFFENSE" description="*********************************************** &lt;br/&gt;3934, Theft from Vehicle&lt;br/&gt;"/><marker lat="40.416565046036247" lng="-80.004963080790716" zone="Zone 3" incidentdate="2014-10-25" incidenttime="16:59:00" incidentnumber="14212981" address="700 block Gearing Ave" type="OFFENSE" description="*********************************************** &lt;br/&gt;9496, Dead on Arrival (DOA)&lt;br/&gt;"/><marker lat="40.454016520179565" lng="-79.895644292400064" zone="Zone 5" incidentdate="2014-10-25" incidenttime="17:16:00" incidentnumber="14213012" address="7300 block Hamilton Ave" type="OFFENSE" description="*********************************************** &lt;br/&gt;9999, 9999 - (Misc. Incident):&lt;br/&gt;"/><marker lat="40.462207375257691" lng="-79.911069672048214" zone="Zone 5" incidentdate="2014-10-25" incidenttime="17:40:00" incidentnumber="14213025" address="Meadow St &amp; Lowell St" type="ARREST" description="*********************************************** &lt;br/&gt;13(a)(31), Marijuana: Possession Small Amount&lt;br/&gt;13(a)(16), Possession of Controlled Substance&lt;br/&gt;3714, Careless Driving&lt;br/&gt;13(a)(30), Possession w/ Intent to Del. Controlled Substance&lt;br/&gt;1332, Display of Registration Plate.&lt;br/&gt;"/><marker lat="40.462207375257691" lng="-79.911069672048214" zone="Zone 5" incidentdate="2014-10-25" incidenttime="17:38:00" incidentnumber="14213025" address="Meadow St &amp; Lowell St" type="OFFENSE" description="*********************************************** &lt;br/&gt;13(a)(31), Marijuana: Possession Small Amount&lt;br/&gt;13(a)(16), Possession of Controlled Substance&lt;br/&gt;3714, Careless Driving&lt;br/&gt;13(a)(30), Possession w/ Intent to Del. Controlled Substance&lt;br/&gt;1332, Display of Registration Plate.&lt;br/&gt;"/><marker lat="40.46337862105085" lng="-79.900522846487931" zone="Zone 5" incidentdate="2014-10-25" incidenttime="18:09:00" incidentnumber="14213046" address="6900 block UPLAND St" type="ARREST" description="*********************************************** &lt;br/&gt;13(a)(31), Marijuana: Possession Small Amount&lt;br/&gt;"/><marker lat="40.46337862105085" lng="-79.900522846487931" zone="Zone 5" incidentdate="2014-10-25" incidenttime="18:09:00" incidentnumber="14213046" address="6900 block UPLAND St" type="OFFENSE" description="*********************************************** &lt;br/&gt;13(a)(31), Marijuana: Possession Small Amount&lt;br/&gt;"/><marker lat="40.477787069932234" lng="-80.029068922201432" zone="Zone 1" incidentdate="2014-10-25" incidenttime="03:00:00" incidentnumber="14213051" address="1100 block Woods Run Ave" type="OFFENSE" description="*********************************************** &lt;br/&gt;3921, Theft by Unlawful Taking or Disposition.&lt;br/&gt;"/><marker lat="40.44628429501789" lng="-80.009554768900912" zone="Zone 1" incidentdate="2014-10-25" incidenttime="18:30:00" incidentnumber="14213055" address="200 block North Shore Dr" type="OFFENSE" description="*********************************************** &lt;br/&gt;9504, Lost Property&lt;br/&gt;"/><marker lat="40.410409269177919" lng="-79.990349653188431" zone="Zone 3" incidentdate="2014-10-25" incidenttime="18:38:00" incidentnumber="14213056" address="Brownsville Rd &amp; Suncrest St" type="OFFENSE" description="*********************************************** &lt;br/&gt;2709(a)(1), Harassment by Physical Contact, or Attempts or Threats&lt;br/&gt;5126, Flight to Avoid Apprehension, Trial or Punishment.&lt;br/&gt;2706, Terroristic Threats.&lt;br/&gt;"/><marker lat="40.443880384697444" lng="-80.053703950718187" zone="Zone 6" incidentdate="2014-10-25" incidenttime="19:30:00" incidentnumber="14213098" address="900 block Woodlow St" type="OFFENSE" description="*********************************************** &lt;br/&gt;3502, Burglary.&lt;br/&gt;"/><marker lat="40.439517079185478" lng="-80.05932981262967" zone="Zone 6" incidentdate="2014-10-25" incidenttime="18:00:00" incidentnumber="14213113" address="1600 block Ridenour Ave" type="OFFENSE" description="*********************************************** &lt;br/&gt;029, Missing Juvenile&lt;br/&gt;"/><marker lat="40.443580942147605" lng="-79.979979097296493" zone="Zone 2" incidentdate="2014-10-25" incidenttime="20:35:00" incidentnumber="14213134" address="2000 block Centre Ave" type="OFFENSE" description="*********************************************** &lt;br/&gt;2701(a)(3), Simple Assault - Attempts by Physical Menace&lt;br/&gt;5503, Disorderly Conduct.&lt;br/&gt;5505, Public Drunkenness&lt;br/&gt;3304, Criminal Mischief.&lt;br/&gt;"/><marker lat="40.443580942147605" lng="-79.979979097296493" zone="Zone 2" incidentdate="2014-10-25" incidenttime="20:40:00" incidentnumber="14213134" address="2000 block Centre Ave" type="ARREST" description="*********************************************** &lt;br/&gt;2701(a)(3), Simple Assault - Attempts by Physical Menace&lt;br/&gt;5503, Disorderly Conduct.&lt;br/&gt;5505, Public Drunkenness&lt;br/&gt;3304, Criminal Mischief.&lt;br/&gt;"/><marker lat="40.429079238999897" lng="-80.040172609720145" zone="Zone 6" incidentdate="2014-10-25" incidenttime="20:50:00" incidentnumber="14213143" address="500 block Greentree Rd" type="OFFENSE" description="*********************************************** &lt;br/&gt;9999, 9999 - (Misc. Incident):&lt;br/&gt;"/><marker lat="40.466763009954917" lng="-80.034127410427146" zone="Zone 1" incidentdate="2014-10-25" incidenttime="21:33:00" incidentnumber="14213169" address="Woodland Ave &amp; California Ave" type="OFFENSE" description="*********************************************** &lt;br/&gt;1543, Driving While Operating Privilege is Suspended or Revoked.&lt;br/&gt;3323, Stop Signs and Yield Signs.&lt;br/&gt;3802(a)(1), DUI - General Impairment&lt;br/&gt;3802(b), DUI - High Rate of Alchol - BAC &gt;=.10% &lt;.16%&lt;br/&gt;"/><marker lat="40.466763009954917" lng="-80.034127410427146" zone="Zone 1" incidentdate="2014-10-25" incidenttime="21:43:00" incidentnumber="14213169" address="Woodland Ave &amp; California Ave" type="ARREST" description="*********************************************** &lt;br/&gt;1543, Driving While Operating Privilege is Suspended or Revoked.&lt;br/&gt;3323, Stop Signs and Yield Signs.&lt;br/&gt;3802(a)(1), DUI - General Impairment&lt;br/&gt;3802(b), DUI - High Rate of Alchol - BAC &gt;=.10% &lt;.16%&lt;br/&gt;"/><marker lat="40.464565858004221" lng="-80.028548787723139" zone="Zone 1" incidentdate="2014-10-25" incidenttime="22:30:00" incidentnumber="14213184" address="Sorrell St &amp; Halsey Pl" type="OFFENSE" description="*********************************************** &lt;br/&gt;9999, 9999 - (Misc. Incident):&lt;br/&gt;"/></markers>
